colosseum/__init__.py
colosseum/colors.py
colosseum/constants.py
colosseum/declaration.py
colosseum/dimensions.py
colosseum/engine.py
colosseum/parser.py
colosseum/units.py
colosseum/utils.py
colosseum-0.2.0.dist-info/DESCRIPTION.rst
colosseum-0.2.0.dist-info/METADATA
colosseum-0.2.0.dist-info/RECORD
colosseum-0.2.0.dist-info/WHEEL
colosseum-0.2.0.dist-info/metadata.json
colosseum-0.2.0.dist-info/pbr.json
colosseum-0.2.0.dist-info/top_level.txt
tests/engine/__init__.py
tests/engine/test_ua_border_sizes.py
tests/engine/block_layout/__init__.py
tests/engine/block_layout/test_block_non_replaced_normal_flow.py
tests/engine/block_layout/test_child_layout.py
tests/engine/inline_layout/__init__.py
tests/engine/inline_layout/test_inline_non_replaced.py
tests/engine/inline_layout/test_inline_replaced.py
tests/web_platform/__init__.py
tests/web_platform/CSS2/__init__.py
tests/web_platform/CSS2/abspos/__init__.py
tests/web_platform/CSS2/abspos/test_abspos_containing_block_initial.py
tests/web_platform/CSS2/box/__init__.py
tests/web_platform/CSS2/box/test_ltr_basic.py
tests/web_platform/CSS2/box/test_ltr_ib.py
tests/web_platform/CSS2/box/test_ltr_span_only.py
tests/web_platform/CSS2/box/test_ltr_span_only_ib.py
tests/web_platform/CSS2/box/test_rtl_basic.py
tests/web_platform/CSS2/box/test_rtl_ib.py
tests/web_platform/CSS2/box/test_rtl_linebreak.py
tests/web_platform/CSS2/box/test_rtl_span_only.py
tests/web_platform/CSS2/box/test_rtl_span_only_ib.py
tests/web_platform/CSS2/box_display/__init__.py
tests/web_platform/CSS2/box_display/test_anonymous_box_generation.py
tests/web_platform/CSS2/box_display/test_anonymous_boxes_inheritance.py
tests/web_platform/CSS2/box_display/test_anonymous_inline_whitespace.py
tests/web_platform/CSS2/box_display/test_block_in_inline.py
tests/web_platform/CSS2/box_display/test_block_in_inline_relpos.py
tests/web_platform/CSS2/box_display/test_box_generation.py
tests/web_platform/CSS2/box_display/test_containing_block.py
tests/web_platform/CSS2/box_display/test_delete_block_in_inlines_beginning.py
tests/web_platform/CSS2/box_display/test_delete_block_in_inlines_end.py
tests/web_platform/CSS2/box_display/test_delete_block_in_inlines_middle.py
